{
    "limitClass": "ChannelLimit",
    "id": 24021109813,
    "reference": "2402.11098",
    "source": "https://doi.org/10.17182/hepdata.132367.v2/t57",
    "citeKey": "CMS:2024ulc",
    "collider": "LHC13",
    "experiment": "CMS",
    "luminosity": 138.0,
    "process": {
        "channels": [
            [
                "HZ",
                "tautau"
            ]
        ]
    },
    "analysis": {
        "massResolution": {
            "absolute": 5,
            "relative": 0.15
        },
        "grid": {
            "mass": [
                15.0,
                20.0,
                25.0,
                30.0,
                40.0,
                50.0,
                60.0,
                70.0,
                75.0,
                90.0,
                100.0,
                108.0
            ]
        },
        "limit": {
            "observed": [
                236.59,
                7.2294,
                2.0522,
                1.0267,
                0.75447,
                0.62682,
                0.4955,
                0.46309,
                0.41018,
                0.25553,
                0.19045,
                0.14691
            ],
            "expected": [
                484.87,
                13.595,
                3.9941,
                1.9177,
                0.96632,
                0.62988,
                0.44775,
                0.39258,
                0.36875,
                0.30634,
                0.25397,
                0.22157
            ]
        }
    }
}