{
    "limitClass": "ChannelLimit",
    "id": 1607035612,
    "reference": "1607.03561",
    "source": "p. 7",
    "citeKey": "CMS:2016cvq",
    "collider": "LHC8",
    "experiment": "CMS",
    "luminosity": 19.7,
    "process": {
        "channels": [
            [
                "ggH",
                "emu"
            ],
            [
                "vbfH",
                "emu"
            ],
            [
                "HZ",
                "emu"
            ],
            [
                "HW",
                "emu"
            ]
        ]
    },
    "constraints": [
        {
            "modelLike": "SMHiggsInterp",
            "process": {
                "channels": [
                    [
                        "ggH",
                        "none"
                    ],
                    [
                        "vbfH",
                        "none"
                    ],
                    [
                        "HZ",
                        "none"
                    ],
                    [
                        "HW",
                        "none"
                    ]
                ]
            }
        }
    ],
    "normalization": {
        "reference": "SMHiggsInterp",
        "process": {
            "channels": [
                [
                    "ggH",
                    "none"
                ],
                [
                    "vbfH",
                    "none"
                ],
                [
                    "HZ",
                    "none"
                ],
                [
                    "HW",
                    "none"
                ]
            ]
        }
    },
    "analysis": {
        "massResolution": {
            "relative": 0,
            "absolute": 6
        },
        "grid": {
            "mass": [
                125.0
            ]
        },
        "limit": {
            "observed": [
                0.00035
            ],
            "expected": [
                0.00048
            ]
        }
    }
}